perennityai_viz/__init__.py
perennityai_viz/main.py
perennityai_viz/data_visualization/__init__.py
perennityai_viz/data_visualization/data_visualizer.py
perennityai_viz/utils/__init__.py
perennityai_viz/utils/csv_handler.py
perennityai_viz/utils/feature_header.py
perennityai_viz/utils/logger.py
perennityai_viz/utils/tfrecord_processor.py
perennityai_viz-0.1.0.dist-info/LICENSE
perennityai_viz-0.1.0.dist-info/METADATA
perennityai_viz-0.1.0.dist-info/WHEEL
perennityai_viz-0.1.0.dist-info/entry_points.txt
perennityai_viz-0.1.0.dist-info/top_level.txt
perennityai_viz-0.1.0.dist-info/RECORD
